{"legislative_session": "2025-2026", "identifier": "HF 1886", "title": "Regional facility for housing and senior nutrition services programs funding provided, bonds issued, and money appropriated.", "from_organization": "~{\"classification\": \"lower\"}", "classification": ["bill"], "subject": ["Bonds", "Housing and Housing Finance Agency", "Senior Citizens"], "abstracts": [], "other_titles": [], "other_identifiers": [], "actions": [{"description": "Introduction and first reading, referred to Capital Investment", "date": "2025-03-05", "organization_id": "~{\"classification\": \"lower\"}", "classification": ["introduction", "referral-committee"], "related_entities": []}], "sponsorships": [{"name": "Igo", "classification": "primary", "entity_type": "person", "primary": true, "person_id": "~{\"name\": \"Igo\"}", "organization_id": null}], "related_bills": [], "versions": [{"note": "Introduction", "links": [{"url": "https://www.revisor.mn.gov/bills/94/2025/0/HF/1886/versions/0/", "media_type": "text/html"}, {"url": "https://www.revisor.mn.gov/bills/94/2025/0/HF/1886/versions/0/pdf/", "media_type": "application/pdf"}], "date": "2025-03-04", "classification": ""}], "documents": [], "citations": [], "sources": [{"url": "https://www.revisor.mn.gov/bills/94/2025/0/HF/1886?body=House", "note": ""}], "extras": {}, "jurisdiction": {"id": "ocd-jurisdiction/country:us/state:mn/government", "name": "Minnesota", "classification": "state", "division_id": "ocd-division/country:us/state:mn"}, "scraped_at": "2025-12-30T08:44:17+00:00", "_id": "b9d1e682-e55b-11f0-9810-3e2cc547d626"}